langchain_progress/__init__.py
langchain_progress/progress_manager.py
langchain_progress/utils/__init__.py
langchain_progress/utils/constants.py
langchain_progress/utils/import_utils.py
langchain_progress/wrappers.py
langchain_progress-0.1.0.dist-info/LICENSE
langchain_progress-0.1.0.dist-info/METADATA
langchain_progress-0.1.0.dist-info/WHEEL
langchain_progress-0.1.0.dist-info/RECORD
