Metadata-Version: 2.1
Name: langchain-progress
Version: 0.1.0
Summary: Wrapper for nicely displaying progress bars for langchain embedding components when using multiprocessing or ray.
Home-page: https://github.com/wrmthorne/langchain-progress
License: MIT
Keywords: Langchain,progress,ray,wrapper,langchain_community,multiprocessing,tqdm
Author: William Thorne
Author-email: wthorne1@sheffield.ac.uk
Requires-Python: >=3.9,<4.0
Classifier: Development Status :: 3 - Alpha
Classifier: Intended Audience :: Developers
Classifier: License :: OSI Approved :: MIT License
Classifier: Programming Language :: Python :: 3
Classifier: Programming Language :: Python :: 3.9
Classifier: Programming Language :: Python :: 3.10
Classifier: Programming Language :: Python :: 3.11
Classifier: Programming Language :: Python :: 3.12
Requires-Dist: langchain-community (<=0.0.28)
Project-URL: Repository, https://github.com/wrmthorne/langchain-progress
